{
  "generated_at": "2026-04-23T12:05:06.072Z",
  "repo": "rebase-network/who-is-hiring",
  "issue_number": 1111,
  "raw_source": {
    "number": 1111,
    "url": "https://github.com/rebase-network/who-is-hiring/issues/1111",
    "title": "[remote] RREX诚聘合约后端工程师/Flutter开发工程师/法务合规经理/券商负责人/财务实习生/HR/SSC -岗位薪资面议",
    "body": "## 公司/团队介绍\nRREX 是一家把“快”和“自由”做到极致的交易平台。我们用一个标准定义自己：“极速执行，自由而生”。我们相信，平台的真正价值在于能否做到极致执行、安全可靠，让用户在任何行情下都能更快出手、更稳成交，并始终自主掌控资产。\n\nRREX 以金融级基础设施为核心，围绕“极速”与“可靠”构建系统能力：低延时撮合与毫秒级响应、统一风控与全链路风险机制、以及自主掌控资产、链上透明可查的安全架构。我们打造“交易所 + Web3 钱包 + 区块链”的协同架构，让资产流转无缝且可追溯，兼顾冷钱包级安全与无私钥的用户体验。\n\n在现货与合约等核心交易能力之外，RREX 持续推动“从功能到沉浸互动”的体验升级：预测市场、UM 合约、Tap Trading、真人对决，以及 Live 直播与社交交易等创新玩法，让交易从单一操作走向更强的互动与参与感。\n\nRREX 是一支全球化团队，我们重视执行力，也坚持把产品与工程质量做到位，并以长期主义持续迭代。我们期待与同样追求极致执行与用户自由的伙伴一起，打造下一代交易平台。\n## 薪资福利待遇\n开发者喜欢薪资范围准确的招聘信息。\n此项必须填写，否则 Rebase 公众号和其它媒体渠道可能不会转发。\n\n## 地点\n- 工作地点：Remote：合约后端工程师/Flutter开发工程师/SSC；深圳坐班：法务合规经理/券商负责人/财务实习生/HR\n- 联系方式：TG：@Pancypan   Or   WeChat: xxpan_px\n\n## 工作性质\n\n- 是否全职：全职\n- 是否远程：部分岗位远程：合约后端工程师/Flutter开发工程师/SSC ，部分岗位坐班深圳：法务合规经理/券商负责人/财务实习生/HR\n（请看清楚，坐班岗位无法远程，不接受勿扰，不浪费您时间哦）\n- 时区要求：GMT+8优先\n\n##  岗位信息：\n岗位JD/对应薪资可以私信获取（TG：@Pancypan   Or   WeChat: xxpan_px）\n",
    "comments": [],
    "labels": [],
    "state": "open",
    "created_at": "2026-04-15T04:35:45Z",
    "updated_at": "2026-04-15T04:35:45Z",
    "closed_at": null,
    "author": "pancy899"
  },
  "normalized": {
    "id": 4266254285,
    "number": 1111,
    "url": "https://github.com/rebase-network/who-is-hiring/issues/1111",
    "title": "[remote] RREX诚聘合约后端工程师/Flutter开发工程师/法务合规经理/券商负责人/财务实习生/HR/SSC -岗位薪资面议",
    "company": "RREX",
    "location": "Remote（合约后端工程师/Flutter开发工程师/SSC）；深圳坐班（法务合规经理/券商负责人/财务实习生/HR）",
    "salary": null,
    "salary_min": null,
    "salary_max": null,
    "salary_currency": null,
    "salary_period": null,
    "remote": true,
    "work_mode": "部分岗位远程，部分岗位深圳坐班（坐班岗位无法远程）",
    "timezone": "要求：GMT+8优先",
    "employment_type": "全职",
    "responsibilities": null,
    "requirements": null,
    "contact_channels": [
      "TG：@Pancypan   Or   WeChat: xxpan_px",
      "telegram:@Pancypan",
      "wechat:xxpan_px",
      "@Pancypan",
      "xxpan_px"
    ],
    "completeness_score": 64,
    "completeness_grade": "D",
    "missing_fields": [
      "salary",
      "responsibilities",
      "requirements"
    ],
    "weak_fields": [
      "contact"
    ],
    "risk_flags": [],
    "score_breakdown": {
      "title": {
        "earned": 10,
        "max": 10,
        "source": "title"
      },
      "company": {
        "earned": 14,
        "max": 14,
        "source": "derived"
      },
      "location": {
        "earned": 9,
        "max": 9,
        "source": "body"
      },
      "salary": {
        "earned": 0,
        "max": 14,
        "source": "none"
      },
      "responsibilities": {
        "earned": 0,
        "max": 11,
        "source": "none"
      },
      "requirements": {
        "earned": 0,
        "max": 9,
        "source": "none"
      },
      "work_mode": {
        "earned": 5,
        "max": 5,
        "source": "body"
      },
      "employment_type": {
        "earned": 4,
        "max": 4,
        "source": "body"
      },
      "contact_channels": {
        "earned": 13,
        "max": 15,
        "source": "body"
      },
      "credibility": {
        "earned": 9,
        "max": 9,
        "source": null
      }
    },
    "field_sources": {
      "title": "title",
      "company": "derived",
      "location": "body",
      "salary": "none",
      "work_mode": "body",
      "employment_type": "body",
      "responsibilities": "none",
      "requirements": "none",
      "contact_channels": "body"
    },
    "comment_supplemented_fields": [],
    "decision_value_score": 41,
    "credibility_score": 9,
    "state": "open",
    "labels": [],
    "created_at": "2026-04-15T04:35:45Z",
    "updated_at": "2026-04-15T04:35:45Z",
    "closed_at": null,
    "rss_updated_at": "2026-04-15T04:35:45.000Z",
    "summary": "## 公司/团队介绍\nRREX 是一家把“快”和“自由”做到极致的交易平台。我们用一个标准定义自己：“极速执行，自由而生”。我们相信，平台的真正价值在于能否做到极致执行、安全可靠，让用户在任何行情下都能更快出手、更稳成交，并始终自主掌控资产。",
    "author": "pancy899"
  },
  "rich": {
    "id": 4266254285,
    "number": 1111,
    "url": "https://github.com/rebase-network/who-is-hiring/issues/1111",
    "title": "[remote] RREX诚聘合约后端工程师/Flutter开发工程师/法务合规经理/券商负责人/财务实习生/HR/SSC -岗位薪资面议",
    "state": "open",
    "labels": [],
    "created_at": "2026-04-15T04:35:45Z",
    "updated_at": "2026-04-15T04:35:45Z",
    "closed_at": null,
    "author": "pancy899",
    "company": "RREX",
    "location": "Remote（合约后端工程师/Flutter开发工程师/SSC）；深圳坐班（法务合规经理/券商负责人/财务实习生/HR）",
    "salary": null,
    "salary_min": null,
    "salary_max": null,
    "salary_currency": null,
    "salary_period": null,
    "remote": true,
    "work_mode": "部分岗位远程，部分岗位深圳坐班（坐班岗位无法远程）",
    "timezone": "要求：GMT+8优先",
    "employment_type": "全职",
    "summary": "## 公司/团队介绍\nRREX 是一家把“快”和“自由”做到极致的交易平台。我们用一个标准定义自己：“极速执行，自由而生”。我们相信，平台的真正价值在于能否做到极致执行、安全可靠，让用户在任何行情下都能更快出手、更稳成交，并始终自主掌控资产。",
    "responsibilities": [],
    "requirements": [],
    "compensation_notes": [
      "开发者喜欢薪资范围准确的招聘信息。",
      "此项必须填写，否则 Rebase 公众号和其它媒体渠道可能不会转发。"
    ],
    "contact_details": [
      "TG：@Pancypan   Or   WeChat: xxpan_px",
      "telegram:@Pancypan",
      "wechat:xxpan_px",
      "@Pancypan",
      "xxpan_px"
    ],
    "sections": [
      {
        "title": "公司/团队介绍",
        "paragraphs": [
          "RREX 是一家把“快”和“自由”做到极致的交易平台。我们用一个标准定义自己：“极速执行，自由而生”。我们相信，平台的真正价值在于能否做到极致执行、安全可靠，让用户在任何行情下都能更快出手、更稳成交，并始终自主掌控资产。",
          "RREX 以金融级基础设施为核心，围绕“极速”与“可靠”构建系统能力：低延时撮合与毫秒级响应、统一风控与全链路风险机制、以及自主掌控资产、链上透明可查的安全架构。我们打造“交易所 + Web3 钱包 + 区块链”的协同架构，让资产流转无缝且可追溯，兼顾冷钱包级安全与无私钥的用户体验。",
          "在现货与合约等核心交易能力之外，RREX 持续推动“从功能到沉浸互动”的体验升级：预测市场、UM 合约、Tap Trading、真人对决，以及 Live 直播与社交交易等创新玩法，让交易从单一操作走向更强的互动与参与感。",
          "RREX 是一支全球化团队，我们重视执行力，也坚持把产品与工程质量做到位，并以长期主义持续迭代。我们期待与同样追求极致执行与用户自由的伙伴一起，打造下一代交易平台。"
        ],
        "bullets": []
      },
      {
        "title": "薪资福利待遇",
        "paragraphs": [
          "开发者喜欢薪资范围准确的招聘信息。",
          "此项必须填写，否则 Rebase 公众号和其它媒体渠道可能不会转发。"
        ],
        "bullets": []
      },
      {
        "title": "地点",
        "paragraphs": [],
        "bullets": [
          "工作地点：Remote：合约后端工程师/Flutter开发工程师/SSC；深圳坐班：法务合规经理/券商负责人/财务实习生/HR",
          "联系方式：TG：@Pancypan   Or   WeChat: xxpan_px"
        ]
      },
      {
        "title": "工作性质",
        "paragraphs": [
          "（请看清楚，坐班岗位无法远程，不接受勿扰，不浪费您时间哦）"
        ],
        "bullets": [
          "是否全职：全职",
          "是否远程：部分岗位远程：合约后端工程师/Flutter开发工程师/SSC ，部分岗位坐班深圳：法务合规经理/券商负责人/财务实习生/HR",
          "时区要求：GMT+8优先"
        ]
      },
      {
        "title": "岗位信息",
        "paragraphs": [
          "岗位JD/对应薪资可以私信获取（TG：@Pancypan   Or   WeChat: xxpan_px）"
        ],
        "bullets": []
      }
    ],
    "narrative": [
      "## 公司/团队介绍 RREX 是一家把“快”和“自由”做到极致的交易平台。我们用一个标准定义自己：“极速执行，自由而生”。我们相信，平台的真正价值在于能否做到极致执行、安全可靠，让用户在任何行情下都能更快出手、更稳成交，并始终自主掌控资产。",
      "RREX 以金融级基础设施为核心，围绕“极速”与“可靠”构建系统能力：低延时撮合与毫秒级响应、统一风控与全链路风险机制、以及自主掌控资产、链上透明可查的安全架构。我们打造“交易所 + Web3 钱包 + 区块链”的协同架构，让资产流转无缝且可追溯，兼顾冷钱包级安全与无私钥的用户体验。",
      "在现货与合约等核心交易能力之外，RREX 持续推动“从功能到沉浸互动”的体验升级：预测市场、UM 合约、Tap Trading、真人对决，以及 Live 直播与社交交易等创新玩法，让交易从单一操作走向更强的互动与参与感。",
      "RREX 是一支全球化团队，我们重视执行力，也坚持把产品与工程质量做到位，并以长期主义持续迭代。我们期待与同样追求极致执行与用户自由的伙伴一起，打造下一代交易平台。 ## 薪资福利待遇 开发者喜欢薪资范围准确的招聘信息。 此项必须填写，否则 Rebase 公众号和其它媒体渠道可能不会转发。",
      "## 地点 - 工作地点：Remote：合约后端工程师/Flutter开发工程师/SSC；深圳坐班：法务合规经理/券商负责人/财务实习生/HR - 联系方式：TG：@Pancypan Or WeChat: xxpan_px",
      "## 工作性质",
      "- 是否全职：全职 - 是否远程：部分岗位远程：合约后端工程师/Flutter开发工程师/SSC ，部分岗位坐班深圳：法务合规经理/券商负责人/财务实习生/HR （请看清楚，坐班岗位无法远程，不接受勿扰，不浪费您时间哦） - 时区要求：GMT+8优先",
      "## 岗位信息： 岗位JD/对应薪资可以私信获取（TG：@Pancypan Or WeChat: xxpan_px）"
    ],
    "raw_body": "## 公司/团队介绍\nRREX 是一家把“快”和“自由”做到极致的交易平台。我们用一个标准定义自己：“极速执行，自由而生”。我们相信，平台的真正价值在于能否做到极致执行、安全可靠，让用户在任何行情下都能更快出手、更稳成交，并始终自主掌控资产。\n\nRREX 以金融级基础设施为核心，围绕“极速”与“可靠”构建系统能力：低延时撮合与毫秒级响应、统一风控与全链路风险机制、以及自主掌控资产、链上透明可查的安全架构。我们打造“交易所 + Web3 钱包 + 区块链”的协同架构，让资产流转无缝且可追溯，兼顾冷钱包级安全与无私钥的用户体验。\n\n在现货与合约等核心交易能力之外，RREX 持续推动“从功能到沉浸互动”的体验升级：预测市场、UM 合约、Tap Trading、真人对决，以及 Live 直播与社交交易等创新玩法，让交易从单一操作走向更强的互动与参与感。\n\nRREX 是一支全球化团队，我们重视执行力，也坚持把产品与工程质量做到位，并以长期主义持续迭代。我们期待与同样追求极致执行与用户自由的伙伴一起，打造下一代交易平台。\n## 薪资福利待遇\n开发者喜欢薪资范围准确的招聘信息。\n此项必须填写，否则 Rebase 公众号和其它媒体渠道可能不会转发。\n\n## 地点\n- 工作地点：Remote：合约后端工程师/Flutter开发工程师/SSC；深圳坐班：法务合规经理/券商负责人/财务实习生/HR\n- 联系方式：TG：@Pancypan   Or   WeChat: xxpan_px\n\n## 工作性质\n\n- 是否全职：全职\n- 是否远程：部分岗位远程：合约后端工程师/Flutter开发工程师/SSC ，部分岗位坐班深圳：法务合规经理/券商负责人/财务实习生/HR\n（请看清楚，坐班岗位无法远程，不接受勿扰，不浪费您时间哦）\n- 时区要求：GMT+8优先\n\n##  岗位信息：\n岗位JD/对应薪资可以私信获取（TG：@Pancypan   Or   WeChat: xxpan_px）\n",
    "completeness_score": 64,
    "completeness_grade": "D",
    "missing_fields": [
      "salary",
      "responsibilities",
      "requirements"
    ],
    "weak_fields": [
      "contact"
    ],
    "risk_flags": [],
    "score_breakdown": {
      "title": {
        "earned": 10,
        "max": 10,
        "source": "title"
      },
      "company": {
        "earned": 14,
        "max": 14,
        "source": "derived"
      },
      "location": {
        "earned": 9,
        "max": 9,
        "source": "body"
      },
      "salary": {
        "earned": 0,
        "max": 14,
        "source": "none"
      },
      "responsibilities": {
        "earned": 0,
        "max": 11,
        "source": "none"
      },
      "requirements": {
        "earned": 0,
        "max": 9,
        "source": "none"
      },
      "work_mode": {
        "earned": 5,
        "max": 5,
        "source": "body"
      },
      "employment_type": {
        "earned": 4,
        "max": 4,
        "source": "body"
      },
      "contact_channels": {
        "earned": 13,
        "max": 15,
        "source": "body"
      },
      "credibility": {
        "earned": 9,
        "max": 9,
        "source": null
      }
    },
    "field_sources": {
      "title": "title",
      "company": "derived",
      "location": "body",
      "salary": "none",
      "work_mode": "body",
      "employment_type": "body",
      "responsibilities": "none",
      "requirements": "none",
      "contact_channels": "body"
    },
    "comment_supplemented_fields": [],
    "decision_value_score": 41,
    "credibility_score": 9
  },
  "extraction_trace": null
}
