{
  "generated_at": "2026-04-23T11:30:37.770Z",
  "repo": "rebase-network/who-is-hiring",
  "issue_number": 422,
  "raw_source": {
    "number": 422,
    "url": "https://github.com/rebase-network/who-is-hiring/issues/422",
    "title": "LBank招聘“合约渠道运营/用户增长中台运营”2000-3000U/月",
    "body": "Lbank是一家全球数字资产交易平台。\r\n\r\n薪资待遇：2000美元-3000美元\r\n\r\n2年以上运营/交易所经验，有一线/二线合约渠道运营经验负责代理，KOL的活动运营，数据分析，需求收集和落地英语可作为工作语言工作中高反馈度，高效发现问题解决问题的能力",
    "comments": [
      {
        "body": "欢迎您提交招聘信息，Rebase 会整理招聘内容，通过公众号发出。",
        "author": "github-actions[bot]",
        "created_at": "2024-04-12T15:34:17Z",
        "updated_at": "2024-04-12T15:34:17Z"
      },
      {
        "body": "请补充招聘的联系方式和其他相关信息",
        "author": "elvis6789",
        "created_at": "2024-04-14T13:12:51Z",
        "updated_at": "2024-04-14T13:12:51Z"
      }
    ],
    "labels": [],
    "state": "open",
    "created_at": "2024-04-12T15:34:07Z",
    "updated_at": "2024-04-14T13:12:52Z",
    "closed_at": null,
    "author": "mandy20142014"
  },
  "normalized": {
    "id": 2240397675,
    "number": 422,
    "url": "https://github.com/rebase-network/who-is-hiring/issues/422",
    "title": "LBank招聘“合约渠道运营/用户增长中台运营”2000-3000U/月",
    "company": "LBank",
    "location": null,
    "salary": null,
    "salary_min": null,
    "salary_max": null,
    "salary_currency": null,
    "salary_period": null,
    "remote": false,
    "work_mode": null,
    "timezone": null,
    "employment_type": null,
    "responsibilities": "负责代理、KOL 的活动运营，数据分析，需求收集和落地。",
    "requirements": "2年以上运营/交易所经验；有一线/二线合约渠道运营经验；英语可作为工作语言；工作中高反馈度，高效发现问题解决问题的能力。",
    "contact_channels": [],
    "completeness_score": 44,
    "completeness_grade": "F",
    "missing_fields": [
      "location",
      "salary",
      "work_mode",
      "employment_type",
      "contact"
    ],
    "weak_fields": [
      "responsibilities"
    ],
    "risk_flags": [
      "contact-missing"
    ],
    "score_breakdown": {
      "title": {
        "earned": 10,
        "max": 10,
        "source": "title"
      },
      "company": {
        "earned": 14,
        "max": 14,
        "source": "derived"
      },
      "location": {
        "earned": 0,
        "max": 9,
        "source": "none"
      },
      "salary": {
        "earned": 0,
        "max": 14,
        "source": "none"
      },
      "responsibilities": {
        "earned": 6,
        "max": 11,
        "source": "body"
      },
      "requirements": {
        "earned": 9,
        "max": 9,
        "source": "body"
      },
      "work_mode": {
        "earned": 0,
        "max": 5,
        "source": "none"
      },
      "employment_type": {
        "earned": 0,
        "max": 4,
        "source": "none"
      },
      "contact_channels": {
        "earned": 0,
        "max": 15,
        "source": "none"
      },
      "credibility": {
        "earned": 5,
        "max": 9,
        "source": null
      }
    },
    "field_sources": {
      "title": "title",
      "company": "derived",
      "location": "none",
      "salary": "none",
      "work_mode": "none",
      "employment_type": "none",
      "responsibilities": "body",
      "requirements": "body",
      "contact_channels": "none"
    },
    "comment_supplemented_fields": [],
    "decision_value_score": 25,
    "credibility_score": 5,
    "state": "open",
    "labels": [],
    "created_at": "2024-04-12T15:34:07Z",
    "updated_at": "2024-04-14T13:12:52Z",
    "closed_at": null,
    "rss_updated_at": "2024-04-14T13:12:52.000Z",
    "summary": "Lbank是一家全球数字资产交易平台。",
    "author": "mandy20142014"
  },
  "rich": {
    "id": 2240397675,
    "number": 422,
    "url": "https://github.com/rebase-network/who-is-hiring/issues/422",
    "title": "LBank招聘“合约渠道运营/用户增长中台运营”2000-3000U/月",
    "state": "open",
    "labels": [],
    "created_at": "2024-04-12T15:34:07Z",
    "updated_at": "2024-04-14T13:12:52Z",
    "closed_at": null,
    "author": "mandy20142014",
    "company": "LBank",
    "location": null,
    "salary": null,
    "salary_min": null,
    "salary_max": null,
    "salary_currency": null,
    "salary_period": null,
    "remote": false,
    "work_mode": null,
    "timezone": null,
    "employment_type": null,
    "summary": "Lbank是一家全球数字资产交易平台。",
    "responsibilities": [],
    "requirements": [
      "2年以上运营/交易所经验；有一线/二线合约渠道运营经验；英语可作为工作语言；工作中高反馈度，高效发现问题解决问题的能力。"
    ],
    "compensation_notes": [],
    "contact_details": [],
    "sections": [
      {
        "title": "General",
        "paragraphs": [
          "Lbank是一家全球数字资产交易平台。",
          "薪资待遇：2000美元-3000美元",
          "2年以上运营/交易所经验，有一线/二线合约渠道运营经验负责代理，KOL的活动运营，数据分析，需求收集和落地英语可作为工作语言工作中高反馈度，高效发现问题解决问题的能力"
        ],
        "bullets": []
      }
    ],
    "narrative": [
      "Lbank是一家全球数字资产交易平台。",
      "薪资待遇：2000美元-3000美元",
      "2年以上运营/交易所经验，有一线/二线合约渠道运营经验负责代理，KOL的活动运营，数据分析，需求收集和落地英语可作为工作语言工作中高反馈度，高效发现问题解决问题的能力"
    ],
    "raw_body": "Lbank是一家全球数字资产交易平台。\r\n\r\n薪资待遇：2000美元-3000美元\r\n\r\n2年以上运营/交易所经验，有一线/二线合约渠道运营经验负责代理，KOL的活动运营，数据分析，需求收集和落地英语可作为工作语言工作中高反馈度，高效发现问题解决问题的能力",
    "completeness_score": 44,
    "completeness_grade": "F",
    "missing_fields": [
      "location",
      "salary",
      "work_mode",
      "employment_type",
      "contact"
    ],
    "weak_fields": [
      "responsibilities"
    ],
    "risk_flags": [
      "contact-missing"
    ],
    "score_breakdown": {
      "title": {
        "earned": 10,
        "max": 10,
        "source": "title"
      },
      "company": {
        "earned": 14,
        "max": 14,
        "source": "derived"
      },
      "location": {
        "earned": 0,
        "max": 9,
        "source": "none"
      },
      "salary": {
        "earned": 0,
        "max": 14,
        "source": "none"
      },
      "responsibilities": {
        "earned": 6,
        "max": 11,
        "source": "body"
      },
      "requirements": {
        "earned": 9,
        "max": 9,
        "source": "body"
      },
      "work_mode": {
        "earned": 0,
        "max": 5,
        "source": "none"
      },
      "employment_type": {
        "earned": 0,
        "max": 4,
        "source": "none"
      },
      "contact_channels": {
        "earned": 0,
        "max": 15,
        "source": "none"
      },
      "credibility": {
        "earned": 5,
        "max": 9,
        "source": null
      }
    },
    "field_sources": {
      "title": "title",
      "company": "derived",
      "location": "none",
      "salary": "none",
      "work_mode": "none",
      "employment_type": "none",
      "responsibilities": "body",
      "requirements": "body",
      "contact_channels": "none"
    },
    "comment_supplemented_fields": [],
    "decision_value_score": 25,
    "credibility_score": 5
  },
  "extraction_trace": null
}
