{
  "generated_at": "2026-04-17T10:16:06.723Z",
  "repo": "rebase-network/who-is-hiring",
  "issue_number": 687,
  "raw_source": {
    "number": 687,
    "url": "https://github.com/rebase-network/who-is-hiring/issues/687",
    "title": "[SH] Web3/Wallet/SocialFi 公司诚聘 资深 iOS工程师 薪水OPEN（RMB/USD）",
    "body": "## 公司/团队介绍\n公司成立于20年，公司分布中国、新加坡、加拿大，美国、日本，是以技术为驱动，搭建完善生态链，目前生态已包含：Wallet、SocialFi、NFT、web3身份验证等等，业务和职业的发展提供了足够的空间。\n\n## 薪资福利待遇\nBasic salary+年终+社保缴纳，双休，非常扁平，典型Work Life Balance企业。\n\n## 地点\n- 工作地点：SH\n- 联系方式：TG：@jtx_2023\n\n## 工作性质\n- 是否全职：是\n- 是否远程：否\n- 时区要求：（UTC/GMT+08:00优先，可覆盖核心工作时间，可适应国际分布式团队协作）\n  \n## 岗位要求、职责\nPosition：资深 iOS 工程师\nJob Type：Full-Time ，Onsite （ SH ）\nIndustry: Web3/Wallet/SocialFi\nPS：\n1 、5/10 以上 iOS App 开发经验利，中英熟练；\n2 、精通 Swift 语言，了解 Swift UI ；\n3 、熟悉密码学，有实际架构经验；\n4 、丰富的链上交互经历，熟悉以太坊生态技术。\n（一定需要具备同行业全职背景）\n\n## 工作环境\nWork Life Balance",
    "comments": [
      {
        "body": "欢迎您提交招聘信息，Rebase 会整理招聘内容，通过公众号发出。",
        "author": "github-actions[bot]",
        "created_at": "2025-02-21T01:30:55Z",
        "updated_at": "2025-02-21T01:30:55Z"
      }
    ],
    "labels": [],
    "state": "open",
    "created_at": "2025-02-21T01:30:43Z",
    "updated_at": "2025-02-21T01:30:56Z",
    "closed_at": null,
    "author": "JTX-8"
  },
  "normalized": {
    "id": 2867670380,
    "number": 687,
    "url": "https://github.com/rebase-network/who-is-hiring/issues/687",
    "title": "[SH] Web3/Wallet/SocialFi 公司诚聘 资深 iOS工程师 薪水OPEN（RMB/USD）",
    "company": "Web3/Wallet/SocialFi 公司",
    "location": "SH",
    "salary": "薪水OPEN（RMB/USD）",
    "salary_min": null,
    "salary_max": null,
    "salary_currency": "USD",
    "salary_period": null,
    "remote": false,
    "work_mode": "Onsite （ SH ）",
    "timezone": "要求：（UTC/GMT+08:00优先，可覆盖核心工作时间，可适应国际分布式团队协作）",
    "employment_type": "Full-Time",
    "responsibilities": null,
    "requirements": "5/10 以上 iOS App 开发经验利，中英熟练；精通 Swift 语言，了解 Swift UI；熟悉密码学，有实际架构经验；丰富的链上交互经历，熟悉以太坊生态技术；一定需要具备同行业全职背景",
    "contact_channels": [
      "TG：@jtx_2023",
      "telegram:@jtx_2023"
    ],
    "completeness_score": 77,
    "completeness_grade": "C",
    "missing_fields": [
      "responsibilities"
    ],
    "weak_fields": [
      "salary",
      "contact"
    ],
    "risk_flags": [],
    "score_breakdown": {
      "title": {
        "earned": 10,
        "max": 10,
        "source": "title"
      },
      "company": {
        "earned": 14,
        "max": 14,
        "source": "title"
      },
      "location": {
        "earned": 9,
        "max": 9,
        "source": "body"
      },
      "salary": {
        "earned": 4,
        "max": 14,
        "source": "title"
      },
      "responsibilities": {
        "earned": 0,
        "max": 11,
        "source": "none"
      },
      "requirements": {
        "earned": 9,
        "max": 9,
        "source": "body"
      },
      "work_mode": {
        "earned": 5,
        "max": 5,
        "source": "body"
      },
      "employment_type": {
        "earned": 4,
        "max": 4,
        "source": "body"
      },
      "contact_channels": {
        "earned": 13,
        "max": 15,
        "source": "body"
      },
      "credibility": {
        "earned": 9,
        "max": 9,
        "source": null
      }
    },
    "field_sources": {
      "title": "title",
      "company": "title",
      "location": "body",
      "salary": "title",
      "work_mode": "body",
      "employment_type": "body",
      "responsibilities": "none",
      "requirements": "body",
      "contact_channels": "body"
    },
    "comment_supplemented_fields": [],
    "decision_value_score": 54,
    "credibility_score": 9,
    "state": "open",
    "labels": [],
    "created_at": "2025-02-21T01:30:43Z",
    "updated_at": "2025-02-21T01:30:56Z",
    "closed_at": null,
    "rss_updated_at": "2025-02-21T01:30:56.000Z",
    "summary": "## 公司/团队介绍\n公司成立于20年，公司分布中国、新加坡、加拿大，美国、日本，是以技术为驱动，搭建完善生态链，目前生态已包含：Wallet、SocialFi、NFT、web3身份验证等等，业务和职业的发展提供了足够的空间。",
    "author": "JTX-8"
  },
  "rich": {
    "id": 2867670380,
    "number": 687,
    "url": "https://github.com/rebase-network/who-is-hiring/issues/687",
    "title": "[SH] Web3/Wallet/SocialFi 公司诚聘 资深 iOS工程师 薪水OPEN（RMB/USD）",
    "state": "open",
    "labels": [],
    "created_at": "2025-02-21T01:30:43Z",
    "updated_at": "2025-02-21T01:30:56Z",
    "closed_at": null,
    "author": "JTX-8",
    "company": "Web3/Wallet/SocialFi 公司",
    "location": "SH",
    "salary": "薪水OPEN（RMB/USD）",
    "salary_min": null,
    "salary_max": null,
    "salary_currency": "USD",
    "salary_period": null,
    "remote": false,
    "work_mode": "Onsite （ SH ）",
    "timezone": "要求：（UTC/GMT+08:00优先，可覆盖核心工作时间，可适应国际分布式团队协作）",
    "employment_type": "Full-Time",
    "summary": "## 公司/团队介绍\n公司成立于20年，公司分布中国、新加坡、加拿大，美国、日本，是以技术为驱动，搭建完善生态链，目前生态已包含：Wallet、SocialFi、NFT、web3身份验证等等，业务和职业的发展提供了足够的空间。",
    "responsibilities": [],
    "requirements": [
      "5/10 以上 iOS App 开发经验利，中英熟练；精通 Swift 语言，了解 Swift UI；熟悉密码学，有实际架构经验；丰富的链上交互经历，熟悉以太坊生态技术；一定需要具备同行业全职背景"
    ],
    "compensation_notes": [
      "OPEN（RMB/USD）",
      "Basic salary+年终+社保缴纳，双休，非常扁平，典型Work Life Balance企业。"
    ],
    "contact_details": [
      "TG：@jtx_2023",
      "telegram:@jtx_2023"
    ],
    "sections": [
      {
        "title": "公司/团队介绍",
        "paragraphs": [
          "公司成立于20年，公司分布中国、新加坡、加拿大，美国、日本，是以技术为驱动，搭建完善生态链，目前生态已包含：Wallet、SocialFi、NFT、web3身份验证等等，业务和职业的发展提供了足够的空间。"
        ],
        "bullets": []
      },
      {
        "title": "薪资福利待遇",
        "paragraphs": [
          "Basic salary+年终+社保缴纳，双休，非常扁平，典型Work Life Balance企业。"
        ],
        "bullets": []
      },
      {
        "title": "地点",
        "paragraphs": [],
        "bullets": [
          "工作地点：SH",
          "联系方式：TG：@jtx_2023"
        ]
      },
      {
        "title": "工作性质",
        "paragraphs": [
          "## 岗位要求、职责",
          "Position：资深 iOS 工程师",
          "Job Type：Full-Time ，Onsite （ SH ）",
          "Industry: Web3/Wallet/SocialFi",
          "PS：",
          "1 、5/10 以上 iOS App 开发经验利，中英熟练；",
          "2 、精通 Swift 语言，了解 Swift UI ；",
          "3 、熟悉密码学，有实际架构经验；",
          "4 、丰富的链上交互经历，熟悉以太坊生态技术。",
          "（一定需要具备同行业全职背景）"
        ],
        "bullets": [
          "是否全职：是",
          "是否远程：否",
          "时区要求：（UTC/GMT+08:00优先，可覆盖核心工作时间，可适应国际分布式团队协作）"
        ]
      },
      {
        "title": "工作环境",
        "paragraphs": [
          "Work Life Balance"
        ],
        "bullets": []
      }
    ],
    "narrative": [
      "## 公司/团队介绍 公司成立于20年，公司分布中国、新加坡、加拿大，美国、日本，是以技术为驱动，搭建完善生态链，目前生态已包含：Wallet、SocialFi、NFT、web3身份验证等等，业务和职业的发展提供了足够的空间。",
      "## 薪资福利待遇 Basic salary+年终+社保缴纳，双休，非常扁平，典型Work Life Balance企业。",
      "## 地点 - 工作地点：SH - 联系方式：TG：@jtx_2023",
      "## 工作性质 - 是否全职：是 - 是否远程：否 - 时区要求：（UTC/GMT+08:00优先，可覆盖核心工作时间，可适应国际分布式团队协作）",
      "## 岗位要求、职责 Position：资深 iOS 工程师 Job Type：Full-Time ，Onsite （ SH ） Industry: Web3/Wallet/SocialFi PS： 1 、5/10 以上 iOS App 开发经验利，中英熟练； 2 、精通 Swift 语言，了解 Swift UI ； 3 、熟悉密码学，有实际架构经验； 4 、丰富的链上交互经历，熟悉以太坊生态技术。 （一定需要具备同行业全职背景）",
      "## 工作环境 Work Life Balance"
    ],
    "raw_body": "## 公司/团队介绍\n公司成立于20年，公司分布中国、新加坡、加拿大，美国、日本，是以技术为驱动，搭建完善生态链，目前生态已包含：Wallet、SocialFi、NFT、web3身份验证等等，业务和职业的发展提供了足够的空间。\n\n## 薪资福利待遇\nBasic salary+年终+社保缴纳，双休，非常扁平，典型Work Life Balance企业。\n\n## 地点\n- 工作地点：SH\n- 联系方式：TG：@jtx_2023\n\n## 工作性质\n- 是否全职：是\n- 是否远程：否\n- 时区要求：（UTC/GMT+08:00优先，可覆盖核心工作时间，可适应国际分布式团队协作）\n  \n## 岗位要求、职责\nPosition：资深 iOS 工程师\nJob Type：Full-Time ，Onsite （ SH ）\nIndustry: Web3/Wallet/SocialFi\nPS：\n1 、5/10 以上 iOS App 开发经验利，中英熟练；\n2 、精通 Swift 语言，了解 Swift UI ；\n3 、熟悉密码学，有实际架构经验；\n4 、丰富的链上交互经历，熟悉以太坊生态技术。\n（一定需要具备同行业全职背景）\n\n## 工作环境\nWork Life Balance",
    "completeness_score": 77,
    "completeness_grade": "C",
    "missing_fields": [
      "responsibilities"
    ],
    "weak_fields": [
      "salary",
      "contact"
    ],
    "risk_flags": [],
    "score_breakdown": {
      "title": {
        "earned": 10,
        "max": 10,
        "source": "title"
      },
      "company": {
        "earned": 14,
        "max": 14,
        "source": "title"
      },
      "location": {
        "earned": 9,
        "max": 9,
        "source": "body"
      },
      "salary": {
        "earned": 4,
        "max": 14,
        "source": "title"
      },
      "responsibilities": {
        "earned": 0,
        "max": 11,
        "source": "none"
      },
      "requirements": {
        "earned": 9,
        "max": 9,
        "source": "body"
      },
      "work_mode": {
        "earned": 5,
        "max": 5,
        "source": "body"
      },
      "employment_type": {
        "earned": 4,
        "max": 4,
        "source": "body"
      },
      "contact_channels": {
        "earned": 13,
        "max": 15,
        "source": "body"
      },
      "credibility": {
        "earned": 9,
        "max": 9,
        "source": null
      }
    },
    "field_sources": {
      "title": "title",
      "company": "title",
      "location": "body",
      "salary": "title",
      "work_mode": "body",
      "employment_type": "body",
      "responsibilities": "none",
      "requirements": "body",
      "contact_channels": "body"
    },
    "comment_supplemented_fields": [],
    "decision_value_score": 54,
    "credibility_score": 9
  },
  "extraction_trace": null
}
