{
  "generated_at": "2026-04-21T10:13:20.530Z",
  "repo": "rebase-network/who-is-hiring",
  "issue_number": 900,
  "raw_source": {
    "number": 900,
    "url": "https://github.com/rebase-network/who-is-hiring/issues/900",
    "title": "[Remote]  bloXroute 诚聘 技术支持工程师 薪资open",
    "body": "## 公司/团队介绍\n\nbloXroute驱动着 Web3 世界速度领先的数据层。由顶尖网络技术专家构建，我们运营的高性能区块链分发网络（Blockchain Distribution Network，简称 BDN），深度优化了区块及交易在 Solana、以太坊、BSC、Base 及 TON 等多条链上的传输效率。\n\n通过加速数据广播，bloXroute 能够实现更快的交易速度、更优的交易执行结果以及更高效的网络环境。我们的产品涵盖低延迟交易接口 Trader API、MEV防护方案及以及链上数据流服务，服务于行业领先的交易机构、验证节点与去中心化金融（DeFi）协议。如今，bloXroute 每天处理数百万笔交易，是全球顶尖交易者所信赖的基础设施。\n\nbloXroute 正在寻找一位积极主动、以客户为中心的支持工程师，加入公司技术支持团队直接开展工作。在该岗位上，您将协助解决技术问题，帮助用户处理产品相关疑问，确保他们获得流畅、满意的体验。同时，您需要与工程、业务等跨职能团队紧密协作，共同解决问题并推动产品功能持续优化。\n\n## 薪资福利待遇\n\n薪资 Open, 面议, 40K RMB 起\n\n## 地点\n\n- 居家\n- 联系方式：linda.jiang@bloXroute.com\n\n## 工作性质\n\n- 是否全职：是\n- 是否远程：是\n- 时区要求：（GMT+8优先，可覆盖核心工作时间，可适应国际分布式团队协作）\n  \n## 工作职责\n\n* 为亚太（APAC）地区客户提供一线支持服务\n* 协同 DevOps及工程团队排查并解决问题\n* 协助用户完成基础维护与问题解决\n* 识别不同区块链网络的服务异常与质量短板\n* 明确开发团队及产品团队的质量标准\n* 运用数据提出改进建议，保障整体服务质量\n\n## 岗位要求\n\n* 英语和普通话流利\n* 至少2年技术支持工程师经验\n* 全职远程工作，base亚洲，能覆盖亚洲时区并适应灵活工作安排\n* 具备Linux系统经验\n* 具备AWS云服务经验\n* 拥有区块链与加密货币技术的知识与实践经验\n* 熟悉亚太（APAC）地区加密货币产业者优先\n* 优秀的表达能力，能够将复杂技术信息简化为清晰易懂的内容\n* 兼具创新与创业精神，拥有出色团队协作能力，具备初创公司工作心态",
    "comments": [
      {
        "body": "欢迎您提交招聘信息，Rebase 会整理招聘内容，通过公众号发出。",
        "author": "github-actions[bot]",
        "created_at": "2025-10-24T10:45:30Z",
        "updated_at": "2025-10-24T10:45:30Z"
      }
    ],
    "labels": [],
    "state": "open",
    "created_at": "2025-10-24T10:45:15Z",
    "updated_at": "2025-10-24T10:45:30Z",
    "closed_at": null,
    "author": "lindajiang-glitch"
  },
  "normalized": {
    "id": 3548803102,
    "number": 900,
    "url": "https://github.com/rebase-network/who-is-hiring/issues/900",
    "title": "[Remote]  bloXroute 诚聘 技术支持工程师 薪资open",
    "company": "bloXroute",
    "location": "居家",
    "salary": "40K RMB 起",
    "salary_min": null,
    "salary_max": null,
    "salary_currency": "CNY",
    "salary_period": null,
    "remote": true,
    "work_mode": "是否远程：是",
    "timezone": "要求：（GMT+8优先，可覆盖核心工作时间，可适应国际分布式团队协作）",
    "employment_type": "是否全职：是",
    "responsibilities": "为亚太（APAC）地区客户提供一线支持服务\n协同 DevOps及工程团队排查并解决问题\n协助用户完成基础维护与问题解决\n识别不同区块链网络的服务异常与质量短板\n明确开发团队及产品团队的质量标准\n运用数据提出改进建议，保障整体服务质量\n英语和普通话流利\n至少2年技术支持工程师经验\n全职远程工作，base亚洲，能覆盖亚洲时区并适应灵活工作安排\n拥有区块链与加密货币技术的知识与实践经验\n优秀的表达能力，能够将复杂技术信息简化为清晰易懂的内容\n兼具创新与创业精神，拥有出色团队协作能力，具备初创公司工作心态",
    "requirements": "英语和普通话流利；至少2年技术支持工程师经验；全职远程工作，base亚洲，能覆盖亚洲时区并适应灵活工作安排；具备Linux系统经验；具备AWS云服务经验；拥有区块链与加密货币技术的知识与实践经验；熟悉亚太（APAC）地区加密货币产业者优先；优秀的表达能力，能够将复杂技术信息简化为清晰易懂的内容；兼具创新与创业精神，拥有出色团队协作能力，具备初创公司工作心态",
    "contact_channels": [
      "linda.jiang@bloXroute.com",
      "email:linda.jiang@bloXroute.com"
    ],
    "completeness_score": 96,
    "completeness_grade": "A",
    "missing_fields": [],
    "weak_fields": [
      "salary"
    ],
    "risk_flags": [],
    "score_breakdown": {
      "title": {
        "earned": 10,
        "max": 10,
        "source": "title"
      },
      "company": {
        "earned": 14,
        "max": 14,
        "source": "derived"
      },
      "location": {
        "earned": 9,
        "max": 9,
        "source": "body"
      },
      "salary": {
        "earned": 10,
        "max": 14,
        "source": "body"
      },
      "responsibilities": {
        "earned": 11,
        "max": 11,
        "source": "body"
      },
      "requirements": {
        "earned": 9,
        "max": 9,
        "source": "body"
      },
      "work_mode": {
        "earned": 5,
        "max": 5,
        "source": "body"
      },
      "employment_type": {
        "earned": 4,
        "max": 4,
        "source": "body"
      },
      "contact_channels": {
        "earned": 15,
        "max": 15,
        "source": "body"
      },
      "credibility": {
        "earned": 9,
        "max": 9,
        "source": null
      }
    },
    "field_sources": {
      "title": "title",
      "company": "derived",
      "location": "body",
      "salary": "body",
      "work_mode": "body",
      "employment_type": "body",
      "responsibilities": "body",
      "requirements": "body",
      "contact_channels": "body"
    },
    "comment_supplemented_fields": [],
    "decision_value_score": 73,
    "credibility_score": 9,
    "state": "open",
    "labels": [],
    "created_at": "2025-10-24T10:45:15Z",
    "updated_at": "2025-10-24T10:45:30Z",
    "closed_at": null,
    "rss_updated_at": "2025-10-24T10:45:30.000Z",
    "summary": "## 公司/团队介绍",
    "author": "lindajiang-glitch"
  },
  "rich": {
    "id": 3548803102,
    "number": 900,
    "url": "https://github.com/rebase-network/who-is-hiring/issues/900",
    "title": "[Remote]  bloXroute 诚聘 技术支持工程师 薪资open",
    "state": "open",
    "labels": [],
    "created_at": "2025-10-24T10:45:15Z",
    "updated_at": "2025-10-24T10:45:30Z",
    "closed_at": null,
    "author": "lindajiang-glitch",
    "company": "bloXroute",
    "location": "居家",
    "salary": "40K RMB 起",
    "salary_min": null,
    "salary_max": null,
    "salary_currency": "CNY",
    "salary_period": null,
    "remote": true,
    "work_mode": "是否远程：是",
    "timezone": "要求：（GMT+8优先，可覆盖核心工作时间，可适应国际分布式团队协作）",
    "employment_type": "是否全职：是",
    "summary": "## 公司/团队介绍",
    "responsibilities": [
      "为亚太（APAC）地区客户提供一线支持服务",
      "协同 DevOps及工程团队排查并解决问题",
      "协助用户完成基础维护与问题解决",
      "识别不同区块链网络的服务异常与质量短板",
      "明确开发团队及产品团队的质量标准",
      "运用数据提出改进建议，保障整体服务质量",
      "英语和普通话流利",
      "至少2年技术支持工程师经验",
      "全职远程工作，base亚洲，能覆盖亚洲时区并适应灵活工作安排",
      "拥有区块链与加密货币技术的知识与实践经验",
      "优秀的表达能力，能够将复杂技术信息简化为清晰易懂的内容",
      "兼具创新与创业精神，拥有出色团队协作能力，具备初创公司工作心态"
    ],
    "requirements": [
      "英语和普通话流利；至少2年技术支持工程师经验；全职远程工作，base亚洲，能覆盖亚洲时区并适应灵活工作安排；具备Linux系统经验；具备AWS云服务经验；拥有区块链与加密货币技术的知识与实践经验；熟悉亚太（APAC）地区加密货币产业者优先；优秀的表达能力，能够将复杂技术信息简化为清晰易懂的内容；兼具创新与创业精神，拥有出色团队协作能力，具备初创公司工作心态"
    ],
    "compensation_notes": [
      "Open, 面议, 40K RMB 起",
      "薪资 Open, 面议, 40K RMB 起"
    ],
    "contact_details": [
      "linda.jiang@bloXroute.com",
      "email:linda.jiang@bloXroute.com"
    ],
    "sections": [
      {
        "title": "公司/团队介绍",
        "paragraphs": [
          "bloXroute驱动着 Web3 世界速度领先的数据层。由顶尖网络技术专家构建，我们运营的高性能区块链分发网络（Blockchain Distribution Network，简称 BDN），深度优化了区块及交易在 Solana、以太坊、BSC、Base 及 TON 等多条链上的传输效率。",
          "通过加速数据广播，bloXroute 能够实现更快的交易速度、更优的交易执行结果以及更高效的网络环境。我们的产品涵盖低延迟交易接口 Trader API、MEV防护方案及以及链上数据流服务，服务于行业领先的交易机构、验证节点与去中心化金融（DeFi）协议。如今，bloXroute 每天处理数百万笔交易，是全球顶尖交易者所信赖的基础设施。",
          "bloXroute 正在寻找一位积极主动、以客户为中心的支持工程师，加入公司技术支持团队直接开展工作。在该岗位上，您将协助解决技术问题，帮助用户处理产品相关疑问，确保他们获得流畅、满意的体验。同时，您需要与工程、业务等跨职能团队紧密协作，共同解决问题并推动产品功能持续优化。"
        ],
        "bullets": []
      },
      {
        "title": "薪资福利待遇",
        "paragraphs": [
          "薪资 Open, 面议, 40K RMB 起"
        ],
        "bullets": []
      },
      {
        "title": "地点",
        "paragraphs": [],
        "bullets": [
          "居家",
          "联系方式：linda.jiang@bloXroute.com"
        ]
      },
      {
        "title": "工作性质",
        "paragraphs": [],
        "bullets": [
          "是否全职：是",
          "是否远程：是",
          "时区要求：（GMT+8优先，可覆盖核心工作时间，可适应国际分布式团队协作）"
        ]
      },
      {
        "title": "Responsibilities",
        "paragraphs": [],
        "bullets": [
          "为亚太（APAC）地区客户提供一线支持服务",
          "协同 DevOps及工程团队排查并解决问题",
          "协助用户完成基础维护与问题解决",
          "识别不同区块链网络的服务异常与质量短板",
          "明确开发团队及产品团队的质量标准",
          "运用数据提出改进建议，保障整体服务质量"
        ]
      },
      {
        "title": "Requirements",
        "paragraphs": [],
        "bullets": [
          "英语和普通话流利",
          "至少2年技术支持工程师经验",
          "全职远程工作，base亚洲，能覆盖亚洲时区并适应灵活工作安排",
          "具备Linux系统经验",
          "具备AWS云服务经验",
          "拥有区块链与加密货币技术的知识与实践经验",
          "熟悉亚太（APAC）地区加密货币产业者优先",
          "优秀的表达能力，能够将复杂技术信息简化为清晰易懂的内容",
          "兼具创新与创业精神，拥有出色团队协作能力，具备初创公司工作心态"
        ]
      }
    ],
    "narrative": [
      "## 公司/团队介绍",
      "bloXroute驱动着 Web3 世界速度领先的数据层。由顶尖网络技术专家构建，我们运营的高性能区块链分发网络（Blockchain Distribution Network，简称 BDN），深度优化了区块及交易在 Solana、以太坊、BSC、Base 及 TON 等多条链上的传输效率。",
      "通过加速数据广播，bloXroute 能够实现更快的交易速度、更优的交易执行结果以及更高效的网络环境。我们的产品涵盖低延迟交易接口 Trader API、MEV防护方案及以及链上数据流服务，服务于行业领先的交易机构、验证节点与去中心化金融（DeFi）协议。如今，bloXroute 每天处理数百万笔交易，是全球顶尖交易者所信赖的基础设施。",
      "bloXroute 正在寻找一位积极主动、以客户为中心的支持工程师，加入公司技术支持团队直接开展工作。在该岗位上，您将协助解决技术问题，帮助用户处理产品相关疑问，确保他们获得流畅、满意的体验。同时，您需要与工程、业务等跨职能团队紧密协作，共同解决问题并推动产品功能持续优化。",
      "## 薪资福利待遇",
      "薪资 Open, 面议, 40K RMB 起",
      "## 地点",
      "- 居家 - 联系方式：linda.jiang@bloXroute.com",
      "## 工作性质",
      "- 是否全职：是 - 是否远程：是 - 时区要求：（GMT+8优先，可覆盖核心工作时间，可适应国际分布式团队协作）",
      "## 工作职责",
      "* 为亚太（APAC）地区客户提供一线支持服务 * 协同 DevOps及工程团队排查并解决问题 * 协助用户完成基础维护与问题解决 * 识别不同区块链网络的服务异常与质量短板 * 明确开发团队及产品团队的质量标准 * 运用数据提出改进建议，保障整体服务质量",
      "## 岗位要求",
      "* 英语和普通话流利 * 至少2年技术支持工程师经验 * 全职远程工作，base亚洲，能覆盖亚洲时区并适应灵活工作安排 * 具备Linux系统经验 * 具备AWS云服务经验 * 拥有区块链与加密货币技术的知识与实践经验 * 熟悉亚太（APAC）地区加密货币产业者优先 * 优秀的表达能力，能够将复杂技术信息简化为清晰易懂的内容 * 兼具创新与创业精神，拥有出色团队协作能力，具备初创公司工作心态"
    ],
    "raw_body": "## 公司/团队介绍\n\nbloXroute驱动着 Web3 世界速度领先的数据层。由顶尖网络技术专家构建，我们运营的高性能区块链分发网络（Blockchain Distribution Network，简称 BDN），深度优化了区块及交易在 Solana、以太坊、BSC、Base 及 TON 等多条链上的传输效率。\n\n通过加速数据广播，bloXroute 能够实现更快的交易速度、更优的交易执行结果以及更高效的网络环境。我们的产品涵盖低延迟交易接口 Trader API、MEV防护方案及以及链上数据流服务，服务于行业领先的交易机构、验证节点与去中心化金融（DeFi）协议。如今，bloXroute 每天处理数百万笔交易，是全球顶尖交易者所信赖的基础设施。\n\nbloXroute 正在寻找一位积极主动、以客户为中心的支持工程师，加入公司技术支持团队直接开展工作。在该岗位上，您将协助解决技术问题，帮助用户处理产品相关疑问，确保他们获得流畅、满意的体验。同时，您需要与工程、业务等跨职能团队紧密协作，共同解决问题并推动产品功能持续优化。\n\n## 薪资福利待遇\n\n薪资 Open, 面议, 40K RMB 起\n\n## 地点\n\n- 居家\n- 联系方式：linda.jiang@bloXroute.com\n\n## 工作性质\n\n- 是否全职：是\n- 是否远程：是\n- 时区要求：（GMT+8优先，可覆盖核心工作时间，可适应国际分布式团队协作）\n  \n## 工作职责\n\n* 为亚太（APAC）地区客户提供一线支持服务\n* 协同 DevOps及工程团队排查并解决问题\n* 协助用户完成基础维护与问题解决\n* 识别不同区块链网络的服务异常与质量短板\n* 明确开发团队及产品团队的质量标准\n* 运用数据提出改进建议，保障整体服务质量\n\n## 岗位要求\n\n* 英语和普通话流利\n* 至少2年技术支持工程师经验\n* 全职远程工作，base亚洲，能覆盖亚洲时区并适应灵活工作安排\n* 具备Linux系统经验\n* 具备AWS云服务经验\n* 拥有区块链与加密货币技术的知识与实践经验\n* 熟悉亚太（APAC）地区加密货币产业者优先\n* 优秀的表达能力，能够将复杂技术信息简化为清晰易懂的内容\n* 兼具创新与创业精神，拥有出色团队协作能力，具备初创公司工作心态",
    "completeness_score": 96,
    "completeness_grade": "A",
    "missing_fields": [],
    "weak_fields": [
      "salary"
    ],
    "risk_flags": [],
    "score_breakdown": {
      "title": {
        "earned": 10,
        "max": 10,
        "source": "title"
      },
      "company": {
        "earned": 14,
        "max": 14,
        "source": "derived"
      },
      "location": {
        "earned": 9,
        "max": 9,
        "source": "body"
      },
      "salary": {
        "earned": 10,
        "max": 14,
        "source": "body"
      },
      "responsibilities": {
        "earned": 11,
        "max": 11,
        "source": "body"
      },
      "requirements": {
        "earned": 9,
        "max": 9,
        "source": "body"
      },
      "work_mode": {
        "earned": 5,
        "max": 5,
        "source": "body"
      },
      "employment_type": {
        "earned": 4,
        "max": 4,
        "source": "body"
      },
      "contact_channels": {
        "earned": 15,
        "max": 15,
        "source": "body"
      },
      "credibility": {
        "earned": 9,
        "max": 9,
        "source": null
      }
    },
    "field_sources": {
      "title": "title",
      "company": "derived",
      "location": "body",
      "salary": "body",
      "work_mode": "body",
      "employment_type": "body",
      "responsibilities": "body",
      "requirements": "body",
      "contact_channels": "body"
    },
    "comment_supplemented_fields": [],
    "decision_value_score": 73,
    "credibility_score": 9
  },
  "extraction_trace": null
}
