{
  "generated_at": "2026-04-21T14:37:42.596Z",
  "repo": "rebase-network/who-is-hiring",
  "issue_number": 953,
  "raw_source": {
    "number": 953,
    "url": "https://github.com/rebase-network/who-is-hiring/issues/953",
    "title": "[Remote] CEX/DEX/L2/ZK 公司诚聘 前端/Golang/运维/智能合约/Flutter/C++/量化交易/首席设计师/Perp DEX 运营与市场/产品/合规 薪水RMB/USD",
    "body": "公司/团队介绍\n公司成立于18年CEX/DEX/L2/ZK，为全球提供现货、合约、期权衍生品等交易产品；Office分布香港、新加坡、加拿大、欧美等。\n\n薪资福利待遇\nBasic salary+年终（USDT），双休，国内外团建旅游，足够发展和发挥空间。\n\n地点\n工作地点：Remote\n联系方式：\nTG：@jtx_2023\nE：justinxu268@gmail.com\n\n工作性质\n是否全职：是\n是否远程：是\n时区要求：（GMT+8优先，可覆盖核心工作时间，可适应国际分布式团队协作）\n\n岗位要求、职责\nPosition 一：\n（1）前端工程师（需要有 DEX 实际业务开发经验）\n（2）wb3 交易系统（后端，web3+交易所的开发经验，有撮合交易引擎经验，无技术语言要求）\n（3）Smart Contract Developer/智能合约开发工程师（ DeFi 方向）\n（4）Perp DEX 运营与市场主管（精通DEX赛道，参与过头部交易平台或 DeFi 项目的社区和运营建设或搭建（如 Binance、OKX、Bybit、dYdX、GMX、Hyperliquid、Lighter、Monad 等）。\n（远程办公，需要有相关任职经验）\n（5）SRE运维工程师（DEX方向，最好可以base深圳；SRE，偏业务运维。技术上，要求对AWS，K8S非常熟悉，在高并发的业务场景工作过比较契合）\n\nPosition 二（1-7每个职位3个 HC+）：\n（1）Golang\n（2）Flutter\n（3）测试工程师\n（4）C++交易系统\n（5）前端工程师（ React ）\n（6）前端工程师（ Node.js ）\n（7）产品经理（交易平台）\n（8）Compliance & Licensing Manager\n（远程办公，技术岗位不需要有 web3 赛道任职经验；全日制 211/985 计算机专业本科及以上+至少一段头部互联网大厂任职背景）。\n\nPosition 三：\n（1）资深工程师 3 （Flutter、 IOS 、Android 、WEB 各一位）\n（2）测试 Leader\n（3）运维 Leader （目前人已经 base 海外）\n（4）产品总监\n（5）首席 UI/UX 设计师（ Chief UI/UX Designer ）\n（计算机本科及以上学历，需要 CEX/DEX 赛道任职背景；技术人员需要在深圳现场办公 3/4 个月，住宿/差旅费全报；之后就可以远程办公，其他职位是前期出差，后期一直远程）\n\nPosition 四：\n（1）Execution Quant/Desk Quant\n（ Onsite Hong Kong ，公司可提供 EP ，有 crypto 量化/实盘交易经验）\n（2）Regional Head - Africa\n（ Onsite Hong Kong ；或者前期深圳，后期香港，有 CEX/Web3 相关经验）\n\nPosition 五：\n（1）APAC Community Lead\n（2）DevRel Engineer\n（远程办公，中英文精通，需要有 L2/web3/ZK 相关经验）\n\n\n工作环境\nWork Life Balance，不卷，内部人员学历/背景/技术等综合素质很高。",
    "comments": [
      {
        "body": "欢迎您提交招聘信息，Rebase 会整理招聘内容，通过公众号发出。",
        "author": "github-actions[bot]",
        "created_at": "2025-11-24T13:59:07Z",
        "updated_at": "2025-11-24T13:59:07Z"
      }
    ],
    "labels": [],
    "state": "open",
    "created_at": "2025-11-24T13:58:58Z",
    "updated_at": "2025-11-24T13:59:07Z",
    "closed_at": null,
    "author": "JTX-8"
  },
  "normalized": {
    "id": 3659033755,
    "number": 953,
    "url": "https://github.com/rebase-network/who-is-hiring/issues/953",
    "title": "[Remote] CEX/DEX/L2/ZK 公司诚聘 前端/Golang/运维/智能合约/Flutter/C++/量化交易/首席设计师/Perp DEX 运营与市场/产品/合规 薪水RMB/USD",
    "company": "CEX/DEX/L2/ZK 公司",
    "location": "Remote",
    "salary": "Basic salary+年终（USDT）",
    "salary_min": null,
    "salary_max": null,
    "salary_currency": "USDT",
    "salary_period": null,
    "remote": false,
    "work_mode": "远程办公",
    "timezone": "要求：（GMT+8优先，可覆盖核心工作时间，可适应国际分布式团队协作）",
    "employment_type": "全职",
    "responsibilities": "前端工程师（需要有 DEX 实际业务开发经验）；wb3 交易系统后端开发（web3+交易所开发经验，有撮合交易引擎经验）；Smart Contract Developer（DeFi 方向）；Perp DEX 运营与市场主管（参与社区和运营建设）；SRE 运维（偏业务运维）。另含 Golang、Flutter、测试、C++交易系统、React/Node 前端、产品经理、合规经理、资深工程师、测试/运维 Leader、产品总监、首席 UI/UX、Execution Quant、Regional Head、APAC Community Lead、DevRel Engineer 等岗位。",
    "requirements": "部分岗位要求 DEX/CEX/Web3/L2/ZK 相关经验；SRE 需熟悉 AWS、K8S 且有高并发场景经验；部分技术岗要求全日制 211/985 计算机本科及以上并有头部互联网经历；另有岗位要求中英文精通、crypto 量化/实盘经验或 CEX/Web3 经验。",
    "contact_channels": [
      "email:justinxu268@gmail.com",
      "telegram:@jtx_2023",
      "@jtx_2023",
      "justinxu268@gmail.com"
    ],
    "completeness_score": 90,
    "completeness_grade": "A",
    "missing_fields": [],
    "weak_fields": [
      "salary"
    ],
    "risk_flags": [],
    "score_breakdown": {
      "title": {
        "earned": 10,
        "max": 10,
        "source": "title"
      },
      "company": {
        "earned": 14,
        "max": 14,
        "source": "title"
      },
      "location": {
        "earned": 9,
        "max": 9,
        "source": "body"
      },
      "salary": {
        "earned": 4,
        "max": 14,
        "source": "body"
      },
      "responsibilities": {
        "earned": 11,
        "max": 11,
        "source": "body"
      },
      "requirements": {
        "earned": 9,
        "max": 9,
        "source": "body"
      },
      "work_mode": {
        "earned": 5,
        "max": 5,
        "source": "body"
      },
      "employment_type": {
        "earned": 4,
        "max": 4,
        "source": "body"
      },
      "contact_channels": {
        "earned": 15,
        "max": 15,
        "source": "body"
      },
      "credibility": {
        "earned": 9,
        "max": 9,
        "source": null
      }
    },
    "field_sources": {
      "title": "title",
      "company": "title",
      "location": "body",
      "salary": "body",
      "work_mode": "body",
      "employment_type": "body",
      "responsibilities": "body",
      "requirements": "body",
      "contact_channels": "body"
    },
    "comment_supplemented_fields": [],
    "decision_value_score": 67,
    "credibility_score": 9,
    "state": "open",
    "labels": [],
    "created_at": "2025-11-24T13:58:58Z",
    "updated_at": "2025-11-24T13:59:07Z",
    "closed_at": null,
    "rss_updated_at": "2025-11-24T13:59:07.000Z",
    "summary": "公司/团队介绍\n公司成立于18年CEX/DEX/L2/ZK，为全球提供现货、合约、期权衍生品等交易产品；Office分布香港、新加坡、加拿大、欧美等。",
    "author": "JTX-8"
  },
  "rich": {
    "id": 3659033755,
    "number": 953,
    "url": "https://github.com/rebase-network/who-is-hiring/issues/953",
    "title": "[Remote] CEX/DEX/L2/ZK 公司诚聘 前端/Golang/运维/智能合约/Flutter/C++/量化交易/首席设计师/Perp DEX 运营与市场/产品/合规 薪水RMB/USD",
    "state": "open",
    "labels": [],
    "created_at": "2025-11-24T13:58:58Z",
    "updated_at": "2025-11-24T13:59:07Z",
    "closed_at": null,
    "author": "JTX-8",
    "company": "CEX/DEX/L2/ZK 公司",
    "location": "Remote",
    "salary": "Basic salary+年终（USDT）",
    "salary_min": null,
    "salary_max": null,
    "salary_currency": "USDT",
    "salary_period": null,
    "remote": false,
    "work_mode": "远程办公",
    "timezone": "要求：（GMT+8优先，可覆盖核心工作时间，可适应国际分布式团队协作）",
    "employment_type": "全职",
    "summary": "公司/团队介绍\n公司成立于18年CEX/DEX/L2/ZK，为全球提供现货、合约、期权衍生品等交易产品；Office分布香港、新加坡、加拿大、欧美等。",
    "responsibilities": [],
    "requirements": [
      "部分岗位要求 DEX/CEX/Web3/L2/ZK 相关经验；SRE 需熟悉 AWS、K8S 且有高并发场景经验；部分技术岗要求全日制 211/985 计算机本科及以上并有头部互联网经历；另有岗位要求中英文精通、crypto 量化/实盘经验或 CEX/Web3 经验。"
    ],
    "compensation_notes": [
      "+年终（USDT），双休，国内外团建旅游，足够发展和发挥空间。"
    ],
    "contact_details": [
      "email:justinxu268@gmail.com",
      "telegram:@jtx_2023",
      "@jtx_2023",
      "justinxu268@gmail.com"
    ],
    "sections": [
      {
        "title": "General",
        "paragraphs": [
          "公司/团队介绍",
          "公司成立于18年CEX/DEX/L2/ZK，为全球提供现货、合约、期权衍生品等交易产品；Office分布香港、新加坡、加拿大、欧美等。",
          "薪资福利待遇",
          "Basic salary+年终（USDT），双休，国内外团建旅游，足够发展和发挥空间。",
          "地点",
          "工作地点：Remote"
        ],
        "bullets": []
      },
      {
        "title": "Contact",
        "paragraphs": [
          "TG：@jtx_2023",
          "E：justinxu268@gmail.com",
          "工作性质",
          "是否全职：是",
          "是否远程：是",
          "时区要求：（GMT+8优先，可覆盖核心工作时间，可适应国际分布式团队协作）",
          "岗位要求、职责",
          "Position 一：",
          "（1）前端工程师（需要有 DEX 实际业务开发经验）",
          "（2）wb3 交易系统（后端，web3+交易所的开发经验，有撮合交易引擎经验，无技术语言要求）",
          "（3）Smart Contract Developer/智能合约开发工程师（ DeFi 方向）",
          "（4）Perp DEX 运营与市场主管（精通DEX赛道，参与过头部交易平台或 DeFi 项目的社区和运营建设或搭建（如 Binance、OKX、Bybit、dYdX、GMX、Hyperliquid、Lighter、Monad 等）。",
          "（远程办公，需要有相关任职经验）",
          "（5）SRE运维工程师（DEX方向，最好可以base深圳；SRE，偏业务运维。技术上，要求对AWS，K8S非常熟悉，在高并发的业务场景工作过比较契合）",
          "Position 二（1-7每个职位3个 HC+）：",
          "（1）Golang",
          "（2）Flutter",
          "（3）测试工程师",
          "（4）C++交易系统",
          "（5）前端工程师（ React ）",
          "（6）前端工程师（ Node.js ）",
          "（7）产品经理（交易平台）",
          "（8）Compliance & Licensing Manager",
          "（远程办公，技术岗位不需要有 web3 赛道任职经验；全日制 211/985 计算机专业本科及以上+至少一段头部互联网大厂任职背景）。",
          "Position 三：",
          "（1）资深工程师 3 （Flutter、 IOS 、Android 、WEB 各一位）",
          "（2）测试 Leader",
          "（3）运维 Leader （目前人已经 base 海外）",
          "（4）产品总监",
          "（5）首席 UI/UX 设计师（ Chief UI/UX Designer ）",
          "（计算机本科及以上学历，需要 CEX/DEX 赛道任职背景；技术人员需要在深圳现场办公 3/4 个月，住宿/差旅费全报；之后就可以远程办公，其他职位是前期出差，后期一直远程）",
          "Position 四：",
          "（1）Execution Quant/Desk Quant",
          "（ Onsite Hong Kong ，公司可提供 EP ，有 crypto 量化/实盘交易经验）",
          "（2）Regional Head - Africa",
          "（ Onsite Hong Kong ；或者前期深圳，后期香港，有 CEX/Web3 相关经验）",
          "Position 五：",
          "（1）APAC Community Lead",
          "（2）DevRel Engineer",
          "（远程办公，中英文精通，需要有 L2/web3/ZK 相关经验）",
          "工作环境",
          "Work Life Balance，不卷，内部人员学历/背景/技术等综合素质很高。"
        ],
        "bullets": []
      }
    ],
    "narrative": [
      "公司/团队介绍 公司成立于18年CEX/DEX/L2/ZK，为全球提供现货、合约、期权衍生品等交易产品；Office分布香港、新加坡、加拿大、欧美等。",
      "薪资福利待遇 Basic salary+年终（USDT），双休，国内外团建旅游，足够发展和发挥空间。",
      "地点 工作地点：Remote 联系方式： TG：@jtx_2023 E：justinxu268@gmail.com",
      "工作性质 是否全职：是 是否远程：是 时区要求：（GMT+8优先，可覆盖核心工作时间，可适应国际分布式团队协作）",
      "岗位要求、职责 Position 一： （1）前端工程师（需要有 DEX 实际业务开发经验） （2）wb3 交易系统（后端，web3+交易所的开发经验，有撮合交易引擎经验，无技术语言要求） （3）Smart Contract Developer/智能合约开发工程师（ DeFi 方向） （4）Perp DEX 运营与市场主管（精通DEX赛道，参与过头部交易平台或 DeFi 项目的社区和运营建设或搭建（如 Binance、OKX、Bybit、dYdX、GMX、Hyperliquid、Lighter、Monad 等）。 （远程办公，需要有相关任职经验） （5）SRE运维工程师（DEX方向，最好可以base深圳；SRE，偏业务运维。技术上，要求对AWS，K8S非常熟悉，在高并发的业务场景工作过比较契合）",
      "Position 二（1-7每个职位3个 HC+）： （1）Golang （2）Flutter （3）测试工程师 （4）C++交易系统 （5）前端工程师（ React ） （6）前端工程师（ Node.js ） （7）产品经理（交易平台） （8）Compliance & Licensing Manager （远程办公，技术岗位不需要有 web3 赛道任职经验；全日制 211/985 计算机专业本科及以上+至少一段头部互联网大厂任职背景）。",
      "Position 三： （1）资深工程师 3 （Flutter、 IOS 、Android 、WEB 各一位） （2）测试 Leader （3）运维 Leader （目前人已经 base 海外） （4）产品总监 （5）首席 UI/UX 设计师（ Chief UI/UX Designer ） （计算机本科及以上学历，需要 CEX/DEX 赛道任职背景；技术人员需要在深圳现场办公 3/4 个月，住宿/差旅费全报；之后就可以远程办公，其他职位是前期出差，后期一直远程）",
      "Position 四： （1）Execution Quant/Desk Quant （ Onsite Hong Kong ，公司可提供 EP ，有 crypto 量化/实盘交易经验） （2）Regional Head - Africa （ Onsite Hong Kong ；或者前期深圳，后期香港，有 CEX/Web3 相关经验）",
      "Position 五： （1）APAC Community Lead （2）DevRel Engineer （远程办公，中英文精通，需要有 L2/web3/ZK 相关经验）",
      "工作环境 Work Life Balance，不卷，内部人员学历/背景/技术等综合素质很高。"
    ],
    "raw_body": "公司/团队介绍\n公司成立于18年CEX/DEX/L2/ZK，为全球提供现货、合约、期权衍生品等交易产品；Office分布香港、新加坡、加拿大、欧美等。\n\n薪资福利待遇\nBasic salary+年终（USDT），双休，国内外团建旅游，足够发展和发挥空间。\n\n地点\n工作地点：Remote\n联系方式：\nTG：@jtx_2023\nE：justinxu268@gmail.com\n\n工作性质\n是否全职：是\n是否远程：是\n时区要求：（GMT+8优先，可覆盖核心工作时间，可适应国际分布式团队协作）\n\n岗位要求、职责\nPosition 一：\n（1）前端工程师（需要有 DEX 实际业务开发经验）\n（2）wb3 交易系统（后端，web3+交易所的开发经验，有撮合交易引擎经验，无技术语言要求）\n（3）Smart Contract Developer/智能合约开发工程师（ DeFi 方向）\n（4）Perp DEX 运营与市场主管（精通DEX赛道，参与过头部交易平台或 DeFi 项目的社区和运营建设或搭建（如 Binance、OKX、Bybit、dYdX、GMX、Hyperliquid、Lighter、Monad 等）。\n（远程办公，需要有相关任职经验）\n（5）SRE运维工程师（DEX方向，最好可以base深圳；SRE，偏业务运维。技术上，要求对AWS，K8S非常熟悉，在高并发的业务场景工作过比较契合）\n\nPosition 二（1-7每个职位3个 HC+）：\n（1）Golang\n（2）Flutter\n（3）测试工程师\n（4）C++交易系统\n（5）前端工程师（ React ）\n（6）前端工程师（ Node.js ）\n（7）产品经理（交易平台）\n（8）Compliance & Licensing Manager\n（远程办公，技术岗位不需要有 web3 赛道任职经验；全日制 211/985 计算机专业本科及以上+至少一段头部互联网大厂任职背景）。\n\nPosition 三：\n（1）资深工程师 3 （Flutter、 IOS 、Android 、WEB 各一位）\n（2）测试 Leader\n（3）运维 Leader （目前人已经 base 海外）\n（4）产品总监\n（5）首席 UI/UX 设计师（ Chief UI/UX Designer ）\n（计算机本科及以上学历，需要 CEX/DEX 赛道任职背景；技术人员需要在深圳现场办公 3/4 个月，住宿/差旅费全报；之后就可以远程办公，其他职位是前期出差，后期一直远程）\n\nPosition 四：\n（1）Execution Quant/Desk Quant\n（ Onsite Hong Kong ，公司可提供 EP ，有 crypto 量化/实盘交易经验）\n（2）Regional Head - Africa\n（ Onsite Hong Kong ；或者前期深圳，后期香港，有 CEX/Web3 相关经验）\n\nPosition 五：\n（1）APAC Community Lead\n（2）DevRel Engineer\n（远程办公，中英文精通，需要有 L2/web3/ZK 相关经验）\n\n\n工作环境\nWork Life Balance，不卷，内部人员学历/背景/技术等综合素质很高。",
    "completeness_score": 90,
    "completeness_grade": "A",
    "missing_fields": [],
    "weak_fields": [
      "salary"
    ],
    "risk_flags": [],
    "score_breakdown": {
      "title": {
        "earned": 10,
        "max": 10,
        "source": "title"
      },
      "company": {
        "earned": 14,
        "max": 14,
        "source": "title"
      },
      "location": {
        "earned": 9,
        "max": 9,
        "source": "body"
      },
      "salary": {
        "earned": 4,
        "max": 14,
        "source": "body"
      },
      "responsibilities": {
        "earned": 11,
        "max": 11,
        "source": "body"
      },
      "requirements": {
        "earned": 9,
        "max": 9,
        "source": "body"
      },
      "work_mode": {
        "earned": 5,
        "max": 5,
        "source": "body"
      },
      "employment_type": {
        "earned": 4,
        "max": 4,
        "source": "body"
      },
      "contact_channels": {
        "earned": 15,
        "max": 15,
        "source": "body"
      },
      "credibility": {
        "earned": 9,
        "max": 9,
        "source": null
      }
    },
    "field_sources": {
      "title": "title",
      "company": "title",
      "location": "body",
      "salary": "body",
      "work_mode": "body",
      "employment_type": "body",
      "responsibilities": "body",
      "requirements": "body",
      "contact_channels": "body"
    },
    "comment_supplemented_fields": [],
    "decision_value_score": 67,
    "credibility_score": 9
  },
  "extraction_trace": null
}
